mhn/__init__.py
mhn/model.py
mhn/optimizers.py
mhn/original/CudaFullStateSpace.dll
mhn/original/Likelihood.cp38-win_amd64.pyd
mhn/original/Likelihood.pyx
mhn/original/ModelConstruction.cp38-win_amd64.pyd
mhn/original/ModelConstruction.pxd
mhn/original/ModelConstruction.pyx
mhn/original/PerformanceCriticalCode.cp38-win_amd64.pyd
mhn/original/PerformanceCriticalCode.pxd
mhn/original/PerformanceCriticalCode.pyx
mhn/original/RegularizedOptimization.py
mhn/original/UtilityFunctions.py
mhn/original/__init__.py
mhn/original/cuda_full_state_space.cu
mhn/original/cuda_inverse_by_substitution.cu
mhn/ssr/CudaStateSpaceRestriction.dll
mhn/ssr/__init__.py
mhn/ssr/cuda_state_space_restriction.cu
mhn/ssr/matrix_exponential.cp38-win_amd64.pyd
mhn/ssr/matrix_exponential.pyx
mhn/ssr/regularized_optimization.py
mhn/ssr/state_containers.cp38-win_amd64.pyd
mhn/ssr/state_containers.pxd
mhn/ssr/state_containers.pyx
mhn/ssr/state_space_restriction.cp38-win_amd64.pyd
mhn/ssr/state_space_restriction.pxd
mhn/ssr/state_space_restriction.pyx
mhn-0.0.6.dist-info/LICENSE
mhn-0.0.6.dist-info/METADATA
mhn-0.0.6.dist-info/WHEEL
mhn-0.0.6.dist-info/top_level.txt
mhn-0.0.6.dist-info/RECORD
