Metadata-Version: 2.1
Name: mhn
Version: 0.0.6
Summary: A package to train and work with Mutual Hazard Networks
Author: Stefan Vocht, Kevin Rupp, Y. Linda Hu
Requires-Python: >=3.8
License-File: LICENSE
Requires-Dist: numpy (>=1.23.0)
Requires-Dist: scipy (>=1.8.0)
Requires-Dist: pandas (>=1.5.3)
